MANIFEST.in
setup.py
bin/gwss-parser.py
gwss_parser/__init__.py
gwss_parser/config.py
gwss_parser/log_format.py
gwss_parser/ngx_cfg_monitor.py
gwss_parser/ngx_cfg_utils.py
gwss_parser/ngx_log_field_parser.py
gwss_parser/ngx_log_parser.py
gwss_parser/start.py
gwss_parser/utils.py
gwss_parser.egg-info/PKG-INFO
gwss_parser.egg-info/SOURCES.txt
gwss_parser.egg-info/dependency_links.txt
gwss_parser.egg-info/not-zip-safe
gwss_parser.egg-info/requires.txt
gwss_parser.egg-info/top_level.txt
gwss_parser/common/__init__.py
gwss_parser/common/ipc.py
gwss_parser/common/log_config.py
gwss_parser/common/logger.py
gwss_parser/common/loggerconfig.py
gwss_parser/common/loggingmp.py