Metadata-Version: 1.0
Name: gwss-parser
Version: 1.6.2
Summary: Garena web stats system collector
Home-page: http://github.com/storborg/funniest
Author: Garena Online Ltd
Author-email: tranmt@garena.com
License: MIT
Platform: UNKNOWN
